Workbook

Sheet Reporting Categories
A1: Personal Budget – Reporting Categories
A3: # | B3: Category | C3: Type | D3: Description / Examples | E3: Plaid Mapping
A4: 1 | B4: Income | C4: Income | D4: Paycheck, transfers in, refunds, interest (positive) | E4: Income; Transfer > Payroll; Interest (positive)
A5: 2 | B5: Housing | C5: Expense | D5: Rent, mortgage, property tax, home insurance | E5: Payment > Rent
A6: 3 | B6: Bills & Utilities | C6: Expense | D6: Phone, internet, electric, water, gas, insurance premiums | E6: Utilities; Payment > *; Tax
A7: 4 | B7: Groceries | C7: Expense | D7: Supermarkets, grocery stores, wholesale clubs | E7: Food and Drink > Groceries; Shops > Supermarkets
A8: 5 | B8: Dining Out | C8: Expense | D8: Restaurants, fast food, coffee shops, bars, delivery | E8: Food and Drink > Restaurants; Food and Drink > *
A9: 6 | B9: Transportation | C9: Expense | D9: Gas, parking, public transit, rideshare, car maintenance | E9: Travel > * (non-airline/lodging)
A10: 7 | B10: Shopping | C10: Expense | D10: Retail, Amazon, clothing, electronics, general merchandise | E10: Shops > * (non-supermarket)
A11: 8 | B11: Entertainment | C11: Expense | D11: Streaming services, movies, games, concerts, events | E11: Recreation
A12: 9 | B12: Health | C12: Expense | D12: Pharmacy, doctor visits, gym memberships, medical bills | E12: Healthcare
A13: 10 | B13: Travel | C13: Expense | D13: Flights, hotels, vacation rentals, travel booking | E13: Travel > Airlines; Travel > Lodging
A14: 11 | B14: Subscriptions | C14: Expense | D14: Recurring services (SaaS, news, apps, memberships) | E14: Service > Subscription
A15: 12 | B15: Personal Care | C15: Expense | D15: Haircuts, beauty, spa, cosmetics | E15: Service > Personal Care
... A20: 17 | B20: Other / Uncategorized | C20: Expense | D20: Anything that doesn't fit above; fallback category | E20: Cash Advance; Community; Service > *

Sheet Plaid Category Mapping
A1: Plaid Category → App Category Mapping
A3: Plaid Category (Primary > Secondary) | B3: App Category | C3: Notes
A4: Income | B4: Income | C4: Direct mapping
A5: Transfer > Payroll | B5: Income | C5: Payroll deposits
A6: Interest (positive) | B6: Income | C6: Savings interest, dividends
A7: Bank Fees | B7: Fees & Charges | C7: All bank fee types
A8: Interest (negative) | B8: Fees & Charges | C8: Interest charges on credit
A9: Cash Advance | B9: Other | C9: Rare; flag for review
A10: Community | B10: Other | C10: Community-related services
A11: Food and Drink > Restaurants | B11: Dining Out | C11: Includes fast food, cafes
A12: Food and Drink > Groceries | B12: Groceries | C12: Grocery-specific merchants
A13: Food and Drink > Coffee Shop | B13: Dining Out | C13: Starbucks, etc.
A14: Food and Drink > * | B14: Dining Out | C14: Catch-all food & drink
... A40: Utilities | B40: Bills & Utilities | C40: Electric, water, gas

Sheet Monthly Budget
A1: Monthly Budget – 12-Month Plan
A3: Category | B3: Jan | C3: Feb | D3: Mar | E3: Apr | F3: May | G3: Jun | H3: Jul | I3: Aug | J3: Sep | K3: Oct | L3: Nov | M3: Dec | N3: Annual Total
A4: INCOME
A5: Salary / Paycheck | B5: 0 | C5: 0 | D5: 0 | E5: 0 | F5: 0 | G5: 0 | H5: 0 | I5: 0 | J5: 0 | K5: 0 | L5: 0 | M5: 0 | N5: =SUM(B5:M5)
A6: Side Income | B6: 0 | C6: 0 | D6: 0 | E6: 0 | F6: 0 | G6: 0 | H6: 0 | I6: 0 | J6: 0 | K6: 0 | L6: 0 | M6: 0 | N6: =SUM(B6:M6)
A7: Interest / Dividends | B7: 0 | C7: 0 | D7: 0 | E7: 0 | F7: 0 | G7: 0 | H7: 0 | I7: 0 | J7: 0 | K7: 0 | L7: 0 | M7: 0 | N7: =SUM(B7:M7)
A8: Refunds | B8: 0 | C8: 0 | D8: 0 | E8: 0 | F8: 0 | G8: 0 | H8: 0 | I8: 0 | J8: 0 | K8: 0 | L8: 0 | M8: 0 | N8: =SUM(B8:M8)
A9: Other Income | B9: 0 | C9: 0 | D9: 0 | E9: 0 | F9: 0 | G9: 0 | H9: 0 | I9: 0 | J9: 0 | K9: 0 | L9: 0 | M9: 0 | N9: =SUM(B9:M9)
A10: TOTAL INCOME | B10: =SUM(B5:B9) | C10: =SUM(C5:C9) | D10: =SUM(D5:D9) | E10: =SUM(E5:E9) | F10: =SUM(F5:F9) | G10: =SUM(G5:G9) | H10: =SUM(H5:H9) | I10: =SUM(I5:I9) | ... N10: =SUM(N5:N9)
A12: EXPENSES
A13: Housing | B13: =SUM(B14:B18) | C13: =SUM(C14:C18) | D13: =SUM(D14:D18) | E13: =SUM(E14:E18) | F13: =SUM(F14:F18) | G13: =SUM(G14:G18) | H13: =SUM(H14:H18) | I13: =SUM(I14:I18) | ... N13: =SUM(N14:N18)
A14: Rent / Mortgage | B14: 0 | C14: 0 | D14: 0 | E14: 0 | F14: 0 | G14: 0 | H14: 0 | I14: 0 | J14: 0 | K14: 0 | L14: 0 | M14: 0 | N14: =SUM(B14:M14)
A15: Property Tax | B15: 0 | C15: 0 | D15: 0 | E15: 0 | F15: 0 | G15: 0 | H15: 0 | I15: 0 | J15: 0 | K15: 0 | L15: 0 | M15: 0 | N15: =SUM(B15:M15)
A16: Home Insurance | B16: 0 | C16: 0 | D16: 0 | E16: 0 | F16: 0 | G16: 0 | H16: 0 | I16: 0 | J16: 0 | K16: 0 | L16: 0 | M16: 0 | N16: =SUM(B16:M16)
A17: HOA Fees | B17: 0 | C17: 0 | D17: 0 | E17: 0 | F17: 0 | G17: 0 | H17: 0 | I17: 0 | J17: 0 | K17: 0 | L17: 0 | M17: 0 | N17: =SUM(B17:M17)
A18: Home Maintenance | B18: 0 | C18: 0 | D18: 0 | E18: 0 | F18: 0 | G18: 0 | H18: 0 | I18: 0 | J18: 0 | K18: 0 | L18: 0 | M18: 0 | N18: =SUM(B18:M18)
A19: Bills & Utilities | B19: =SUM(B20:B25) | C19: =SUM(C20:C25) | D19: =SUM(D20:D25) | E19: =SUM(E20:E25) | F19: =SUM(F20:F25) | G19: =SUM(G20:G25) | H19: =SUM(H20:H25) | I19: =SUM(I20:I25) | ... N19: =SUM(N20:N25)
A20: Electric | B20: 0 | C20: 0 | D20: 0 | E20: 0 | F20: 0 | G20: 0 | H20: 0 | I20: 0 | J20: 0 | K20: 0 | L20: 0 | M20: 0 | N20: =SUM(B20:M20)
A21: Water / Sewer | B21: 0 | C21: 0 | D21: 0 | E21: 0 | F21: 0 | G21: 0 | H21: 0 | I21: 0 | J21: 0 | K21: 0 | L21: 0 | M21: 0 | N21: =SUM(B21:M21)
A22: Gas (home) | B22: 0 | C22: 0 | D22: 0 | E22: 0 | F22: 0 | G22: 0 | H22: 0 | I22: 0 | J22: 0 | K22: 0 | L22: 0 | M22: 0 | N22: =SUM(B22:M22)
A23: Internet | B23: 0 | C23: 0 | D23: 0 | E23: 0 | F23: 0 | G23: 0 | H23: 0 | I23: 0 | J23: 0 | K23: 0 | L23: 0 | M23: 0 | N23: =SUM(B23:M23)
A24: Phone | B24: 0 | C24: 0 | D24: 0 | E24: 0 | F24: 0 | G24: 0 | H24: 0 | I24: 0 | J24: 0 | K24: 0 | L24: 0 | M24: 0 | N24: =SUM(B24:M24)
A25: Insurance (auto/health/life) | B25: 0 | C25: 0 | D25: 0 | E25: 0 | F25: 0 | G25: 0 | H25: 0 | I25: 0 | J25: 0 | K25: 0 | L25: 0 | M25: 0 | N25: =SUM(B25:M25)
A26: Groceries | B26: =SUM(B27:B28) | C26: =SUM(C27:C28) | D26: =SUM(D27:D28) | E26: =SUM(E27:E28) | F26: =SUM(F27:F28) | G26: =SUM(G27:G28) | H26: =SUM(H27:H28) | I26: =SUM(I27:I28) | ... N26: =SUM(N27:N28)
A27: Grocery Stores | B27: 0 | C27: 0 | D27: 0 | E27: 0 | F27: 0 | G27: 0 | H27: 0 | I27: 0 | J27: 0 | K27: 0 | L27: 0 | M27: 0 | N27: =SUM(B27:M27)
A28: Wholesale Clubs (Costco, etc.) | B28: 0 | C28: 0 | D28: 0 | E28: 0 | F28: 0 | G28: 0 | H28: 0 | I28: 0 | J28: 0 | K28: 0 | L28: 0 | M28: 0 | N28: =SUM(B28:M28)
A29: Dining Out | B29: =SUM(B30:B33) | C29: =SUM(C30:C33) | D29: =SUM(D30:D33) | E29: =SUM(E30:E33) | F29: =SUM(F30:F33) | G29: =SUM(G30:G33) | H29: =SUM(H30:H33) | I29: =SUM(I30:I33) | ... N29: =SUM(N30:N33)
A30: Restaurants | B30: 0 | C30: 0 | D30: 0 | E30: 0 | F30: 0 | G30: 0 | H30: 0 | I30: 0 | J30: 0 | K30: 0 | L30: 0 | M30: 0 | N30: =SUM(B30:M30)
A31: Fast Food | B31: 0 | C31: 0 | D31: 0 | E31: 0 | F31: 0 | G31: 0 | H31: 0 | I31: 0 | J31: 0 | K31: 0 | L31: 0 | M31: 0 | N31: =SUM(B31:M31)
A32: Coffee Shops | B32: 0 | C32: 0 | D32: 0 | E32: 0 | F32: 0 | G32: 0 | H32: 0 | I32: 0 | J32: 0 | K32: 0 | L32: 0 | M32: 0 | N32: =SUM(B32:M32)
A33: Food Delivery | B33: 0 | C33: 0 | D33: 0 | E33: 0 | F33: 0 | G33: 0 | H33: 0 | I33: 0 | J33: 0 | K33: 0 | L33: 0 | M33: 0 | N33: =SUM(B33:M33)
A34: Transportation | B34: =SUM(B35:B41) | C34: =SUM(C35:C41) | D34: =SUM(D35:D41) | E34: =SUM(E35:E41) | F34: =SUM(F35:F41) | G34: =SUM(G35:G41) | H34: =SUM(H35:H41) | I34: =SUM(I35:I41) | ... N34: =SUM(N35:N41)
A35: Gas (auto) | B35: 0 | C35: 0 | D35: 0 | E35: 0 | F35: 0 | G35: 0 | H35: 0 | I35: 0 | J35: 0 | K35: 0 | L35: 0 | M35: 0 | N35: =SUM(B35:M35)
A36: Car Payment | B36: 0 | C36: 0 | D36: 0 | E36: 0 | F36: 0 | G36: 0 | H36: 0 | I36: 0 | J36: 0 | K36: 0 | L36: 0 | M36: 0 | N36: =SUM(B36:M36)
A37: Car Insurance | B37: 0 | C37: 0 | D37: 0 | E37: 0 | F37: 0 | G37: 0 | H37: 0 | I37: 0 | J37: 0 | K37: 0 | L37: 0 | M37: 0 | N37: =SUM(B37:M37)
A38: Parking | B38: 0 | C38: 0 | D38: 0 | E38: 0 | F38: 0 | G38: 0 | H38: 0 | I38: 0 | J38: 0 | K38: 0 | L38: 0 | M38: 0 | N38: =SUM(B38:M38)
A39: Public Transit | B39: 0 | C39: 0 | D39: 0 | E39: 0 | F39: 0 | G39: 0 | H39: 0 | I39: 0 | J39: 0 | K39: 0 | L39: 0 | M39: 0 | N39: =SUM(B39:M39)
A40: Rideshare (Uber/Lyft) | B40: 0 | C40: 0 | D40: 0 | E40: 0 | F40: 0 | G40: 0 | H40: 0 | I40: 0 | J40: 0 | K40: 0 | L40: 0 | M40: 0 | N40: =SUM(B40:M40)
A41: Car Maintenance | B41: 0 | C41: 0 | D41: 0 | E41: 0 | F41: 0 | G41: 0 | H41: 0 | I41: 0 | J41: 0 | K41: 0 | L41: 0 | M41: 0 | N41: =SUM(B41:M41)
A42: Shopping | B42: =SUM(B43:B47) | C42: =SUM(C43:C47) | D42: =SUM(D43:D47) | E42: =SUM(E43:E47) | F42: =SUM(F43:F47) | G42: =SUM(G43:G47) | H42: =SUM(H43:H47) | I42: =SUM(I43:I47) | ... N42: =SUM(N43:N47)
A43: Clothing | B43: 0 | C43: 0 | D43: 0 | E43: 0 | F43: 0 | G43: 0 | H43: 0 | I43: 0 | J43: 0 | K43: 0 | L43: 0 | M43: 0 | N43: =SUM(B43:M43)
A44: Electronics | B44: 0 | C44: 0 | D44: 0 | E44: 0 | F44: 0 | G44: 0 | H44: 0 | I44: 0 | J44: 0 | K44: 0 | L44: 0 | M44: 0 | N44: =SUM(B44:M44)
A45: Amazon / Online | B45: 0 | C45: 0 | D45: 0 | E45: 0 | F45: 0 | G45: 0 | H45: 0 | I45: 0 | J45: 0 | K45: 0 | L45: 0 | M45: 0 | N45: =SUM(B45:M45)
A46: Home Goods | B46: 0 | C46: 0 | D46: 0 | E46: 0 | F46: 0 | G46: 0 | H46: 0 | I46: 0 | J46: 0 | K46: 0 | L46: 0 | M46: 0 | N46: =SUM(B46:M46)
A47: General Retail | B47: 0 | C47: 0 | D47: 0 | E47: 0 | F47: 0 | G47: 0 | H47: 0 | I47: 0 | J47: 0 | K47: 0 | L47: 0 | M47: 0 | N47: =SUM(B47:M47)
A48: Entertainment | B48: =SUM(B49:B52) | C48: =SUM(C49:C52) | D48: =SUM(D49:D52) | E48: =SUM(E49:E52) | F48: =SUM(F49:F52) | G48: =SUM(G49:G52) | H48: =SUM(H49:H52) | I48: =SUM(I49:I52) | ... N48: =SUM(N49:N52)
A49: Streaming Services | B49: 0 | C49: 0 | D49: 0 | E49: 0 | F49: 0 | G49: 0 | H49: 0 | I49: 0 | J49: 0 | K49: 0 | L49: 0 | M49: 0 | N49: =SUM(B49:M49)
A50: Movies / Events | B50: 0 | C50: 0 | D50: 0 | E50: 0 | F50: 0 | G50: 0 | H50: 0 | I50: 0 | J50: 0 | K50: 0 | L50: 0 | M50: 0 | N50: =SUM(B50:M50)
A51: Games | B51: 0 | C51: 0 | D51: 0 | E51: 0 | F51: 0 | G51: 0 | H51: 0 | I51: 0 | J51: 0 | K51: 0 | L51: 0 | M51: 0 | N51: =SUM(B51:M51)
A52: Hobbies | B52: 0 | C52: 0 | D52: 0 | E52: 0 | F52: 0 | G52: 0 | H52: 0 | I52: 0 | J52: 0 | K52: 0 | L52: 0 | M52: 0 | N52: =SUM(B52:M52)
A53: Health | B53: =SUM(B54:B57) | C53: =SUM(C54:C57) | D53: =SUM(D54:D57) | E53: =SUM(E54:E57) | F53: =SUM(F54:F57) | G53: =SUM(G54:G57) | H53: =SUM(H54:H57) | I53: =SUM(I54:I57) | ... N53: =SUM(N54:N57)
A54: Pharmacy | B54: 0 | C54: 0 | D54: 0 | E54: 0 | F54: 0 | G54: 0 | H54: 0 | I54: 0 | J54: 0 | K54: 0 | L54: 0 | M54: 0 | N54: =SUM(B54:M54)
A55: Doctor / Medical | B55: 0 | C55: 0 | D55: 0 | E55: 0 | F55: 0 | G55: 0 | H55: 0 | I55: 0 | J55: 0 | K55: 0 | L55: 0 | M55: 0 | N55: =SUM(B55:M55)
A56: Gym Membership | B56: 0 | C56: 0 | D56: 0 | E56: 0 | F56: 0 | G56: 0 | H56: 0 | I56: 0 | J56: 0 | K56: 0 | L56: 0 | M56: 0 | N56: =SUM(B56:M56)
A57: Dental / Vision | B57: 0 | C57: 0 | D57: 0 | E57: 0 | F57: 0 | G57: 0 | H57: 0 | I57: 0 | J57: 0 | K57: 0 | L57: 0 | M57: 0 | N57: =SUM(B57:M57)
A58: Travel | B58: =SUM(B59:B61) | C58: =SUM(C59:C61) | D58: =SUM(D59:D61) | E58: =SUM(E59:E61) | F58: =SUM(F59:F61) | G58: =SUM(G59:G61) | H58: =SUM(H59:H61) | I58: =SUM(I59:I61) | ... N58: =SUM(N59:N61)
A59: Flights | B59: 0 | C59: 0 | D59: 0 | E59: 0 | F59: 0 | G59: 0 | H59: 0 | I59: 0 | J59: 0 | K59: 0 | L59: 0 | M59: 0 | N59: =SUM(B59:M59)
A60: Hotels / Lodging | B60: 0 | C60: 0 | D60: 0 | E60: 0 | F60: 0 | G60: 0 | H60: 0 | I60: 0 | J60: 0 | K60: 0 | L60: 0 | M60: 0 | N60: =SUM(B60:M60)
A61: Vacation Activities | B61: 0 | C61: 0 | D61: 0 | E61: 0 | F61: 0 | G61: 0 | H61: 0 | I61: 0 | J61: 0 | K61: 0 | L61: 0 | M61: 0 | N61: =SUM(B61:M61)
A62: Subscriptions | B62: =SUM(B63:B65) | C62: =SUM(C63:C65) | D62: =SUM(D63:D65) | E62: =SUM(E63:E65) | F62: =SUM(F63:F65) | G62: =SUM(G63:G65) | H62: =SUM(H63:H65) | I62: =SUM(I63:I65) | ... N62: =SUM(N63:N65)
A63: Software / SaaS | B63: 0 | C63: 0 | D63: 0 | E63: 0 | F63: 0 | G63: 0 | H63: 0 | I63: 0 | J63: 0 | K63: 0 | L63: 0 | M63: 0 | N63: =SUM(B63:M63)
A64: News / Media | B64: 0 | C64: 0 | D64: 0 | E64: 0 | F64: 0 | G64: 0 | H64: 0 | I64: 0 | J64: 0 | K64: 0 | L64: 0 | M64: 0 | N64: =SUM(B64:M64)
A65: App Subscriptions | B65: 0 | C65: 0 | D65: 0 | E65: 0 | F65: 0 | G65: 0 | H65: 0 | I65: 0 | J65: 0 | K65: 0 | L65: 0 | M65: 0 | N65: =SUM(B65:M65)
A66: Personal Care | B66: =SUM(B67:B68) | C66: =SUM(C67:C68) | D66: =SUM(D67:D68) | E66: =SUM(E67:E68) | F66: =SUM(F67:F68) | G66: =SUM(G67:G68) | H66: =SUM(H67:H68) | I66: =SUM(I67:I68) | ... N66: =SUM(N67:N68)
A67: Haircuts / Salon | B67: 0 | C67: 0 | D67: 0 | E67: 0 | F67: 0 | G67: 0 | H67: 0 | I67: 0 | J67: 0 | K67: 0 | L67: 0 | M67: 0 | N67: =SUM(B67:M67)
A68: Beauty / Cosmetics | B68: 0 | C68: 0 | D68: 0 | E68: 0 | F68: 0 | G68: 0 | H68: 0 | I68: 0 | J68: 0 | K68: 0 | L68: 0 | M68: 0 | N68: =SUM(B68:M68)
A69: Education | B69: =SUM(B70:B71) | C69: =SUM(C70:C71) | D69: =SUM(D70:D71) | E69: =SUM(E70:E71) | F69: =SUM(F70:F71) | G69: =SUM(G70:G71) | H69: =SUM(H70:H71) | I69: =SUM(I70:I71) | ... N69: =SUM(N70:N71)
A70: Tuition / Courses | B70: 0 | C70: 0 | D70: 0 | E70: 0 | F70: 0 | G70: 0 | H70: 0 | I70: 0 | J70: 0 | K70: 0 | L70: 0 | M70: 0 | N70: =SUM(B70:M70)
A71: Books / Supplies | B71: 0 | C71: 0 | D71: 0 | E71: 0 | F71: 0 | G71: 0 | H71: 0 | I71: 0 | J71: 0 | K71: 0 | L71: 0 | M71: 0 | N71: =SUM(B71:M71)
A72: Gifts & Donations | B72: =SUM(B73:B74) | C72: =SUM(C73:C74) | D72: =SUM(D73:D74) | E72: =SUM(E73:E74) | F72: =SUM(F73:F74) | G72: =SUM(G73:G74) | H72: =SUM(H73:H74) | I72: =SUM(I73:I74) | ... N72: =SUM(N73:N74)
A73: Charitable Donations | B73: 0 | C73: 0 | D73: 0 | E73: 0 | F73: 0 | G73: 0 | H73: 0 | I73: 0 | J73: 0 | K73: 0 | L73: 0 | M73: 0 | N73: =SUM(B73:M73)
A74: Gifts | B74: 0 | C74: 0 | D74: 0 | E74: 0 | F74: 0 | G74: 0 | H74: 0 | I74: 0 | J74: 0 | K74: 0 | L74: 0 | M74: 0 | N74: =SUM(B74:M74)
A75: Fees & Charges | B75: =SUM(B76:B78) | C75: =SUM(C76:C78) | D75: =SUM(D76:D78) | E75: =SUM(E76:E78) | F75: =SUM(F76:F78) | G75: =SUM(G76:G78) | H75: =SUM(H76:H78) | I75: =SUM(I76:I78) | ... N75: =SUM(N76:N78)
A76: Bank Fees | B76: 0 | C76: 0 | D76: 0 | E76: 0 | F76: 0 | G76: 0 | H76: 0 | I76: 0 | J76: 0 | K76: 0 | L76: 0 | M76: 0 | N76: =SUM(B76:M76)
A77: ATM Fees | B77: 0 | C77: 0 | D77: 0 | E77: 0 | F77: 0 | G77: 0 | H77: 0 | I77: 0 | J77: 0 | K77: 0 | L77: 0 | M77: 0 | N77: =SUM(B77:M77)
A78: Late Fees / Penalties | B78: 0 | C78: 0 | D78: 0 | E78: 0 | F78: 0 | G78: 0 | H78: 0 | I78: 0 | J78: 0 | K78: 0 | L78: 0 | M78: 0 | N78: =SUM(B78:M78)
A79: Other / Uncategorized | B79: =SUM(B80:B80) | C79: =SUM(C80:C80) | D79: =SUM(D80:D80) | E79: =SUM(E80:E80) | F79: =SUM(F80:F80) | G79: =SUM(G80:G80) | H79: =SUM(H80:H80) | I79: =SUM(I80:I80) | ... N79: =SUM(N80:N80)
A80: Miscellaneous | B80: 0 | C80: 0 | D80: 0 | E80: 0 | F80: 0 | G80: 0 | H80: 0 | I80: 0 | J80: 0 | K80: 0 | L80: 0 | M80: 0 | N80: =SUM(B80:M80)
A81: TOTAL EXPENSES | B81: =B13+B19+B26+B29+B34+B42+B48+B53+B58+B62+B66+B69+B72+B75+B79 | C81: =C13+C19+C26+C29+C34+C42+C48+C53+C58+C62+C66+C69+C72+C75+C79 | D81: =D13+D19+D26+D29+D34+D42+D48+D53+D58+D62+D66+D69+D72+D75+D79 | E81: =E13+E19+E26+E29+E34+E42+E48+E53+E58+E62+E66+E69+E72+E75+E79 | F81: =F13+F19+F26+F29+F34+F42+F48+F53+F58+F62+F66+F69+F72+F75+F79 | G81: =G13+G19+G26+G29+G34+G42+G48+G53+G58+G62+G66+G69+G72+G75+G79 | H81: =H13+H19+H26+H29+H34+H42+H48+H53+H58+H62+H66+H69+H72+H75+H79 | I81: =I13+I19+I26+I29+I34+I42+I48+I53+I58+I62+I66+I69+I72+I75+I79 | ... N81: =N13+N19+N26+N29+N34+N42+N48+N53+N58+N62+N66+N69+N72+N75+N79
A83: NET CASH FLOW | B83: =B10-B81 | C83: =C10-C81 | D83: =D10-D81 | E83: =E10-E81 | F83: =F10-F81 | G83: =G10-G81 | H83: =H10-H81 | I83: =I10-I81 | ... N83: =N10-N81
A84: SAVINGS RATE | B84: =IFERROR(B83/B10,0) | C84: =IFERROR(C83/C10,0) | D84: =IFERROR(D83/D10,0) | E84: =IFERROR(E83/E10,0) | F84: =IFERROR(F83/F10,0) | G84: =IFERROR(G83/G10,0) | H84: =IFERROR(H83/H10,0) | I84: =IFERROR(I83/I10,0) | ... N84: =IFERROR(N83/N10,0)

Sheet Dashboard
A1: Budget Dashboard – Monthly Summary
A3: This dashboard references the 'Monthly Budget' sheet. Enter your data there and this will update automatically.
A5: Total Annual Income | D5: Total Annual Expenses | G5: Annual Net Cash Flow
A6: ='Monthly Budget'!N10 | D6: ='Monthly Budget'!N81 | G6: ='Monthly Budget'!N83
A9: Metric | B9: Jan | C9: Feb | D9: Mar | E9: Apr | F9: May | G9: Jun | H9: Jul | I9: Aug | J9: Sep | K9: Oct | L9: Nov | M9: Dec
A10: Total Income | B10: ='Monthly Budget'!B10 | C10: ='Monthly Budget'!C10 | D10: ='Monthly Budget'!D10 | E10: ='Monthly Budget'!E10 | F10: ='Monthly Budget'!F10 | G10: ='Monthly Budget'!G10 | H10: ='Monthly Budget'!H10 | I10: ='Monthly Budget'!I10 | ... M10: ='Monthly Budget'!M10
A11: Total Expenses | B11: ='Monthly Budget'!B81 | C11: ='Monthly Budget'!C81 | D11: ='Monthly Budget'!D81 | E11: ='Monthly Budget'!E81 | F11: ='Monthly Budget'!F81 | G11: ='Monthly Budget'!G81 | H11: ='Monthly Budget'!H81 | I11: ='Monthly Budget'!I81 | ... M11: ='Monthly Budget'!M81
A12: Net Cash Flow | B12: ='Monthly Budget'!B83 | C12: ='Monthly Budget'!C83 | D12: ='Monthly Budget'!D83 | E12: ='Monthly Budget'!E83 | F12: ='Monthly Budget'!F83 | G12: ='Monthly Budget'!G83 | H12: ='Monthly Budget'!H83 | I12: ='Monthly Budget'!I83 | ... M12: ='Monthly Budget'!M83

Sheet Budget vs Actual
A1: Budget vs Actual – Monthly Comparison
A3: Select Month: | B3: January
A5: Category | B5: Budget | C5: Actual | D5: Variance ($) | E5: Variance (%) | F5: Status
A6: Housing | B6: 0 | C6: 0 | D6: =B6-C6 | E6: =IFERROR((B6-C6)/B6,0) | F6: =IF(C6<=B6,"Under Budget","Over Budget")
A7: Bills & Utilities | B7: 0 | C7: 0 | D7: =B7-C7 | E7: =IFERROR((B7-C7)/B7,0) | F7: =IF(C7<=B7,"Under Budget","Over Budget")
A8: Groceries | B8: 0 | C8: 0 | D8: =B8-C8 | E8: =IFERROR((B8-C8)/B8,0) | F8: =IF(C8<=B8,"Under Budget","Over Budget")
A9: Dining Out | B9: 0 | C9: 0 | D9: =B9-C9 | E9: =IFERROR((B9-C9)/B9,0) | F9: =IF(C9<=B9,"Under Budget","Over Budget")
A10: Transportation | B10: 0 | C10: 0 | D10: =B10-C10 | E10: =IFERROR((B10-C10)/B10,0) | F10: =IF(C10<=B10,"Under Budget","Over Budget")
A11: Shopping | B11: 0 | C11: 0 | D11: =B11-C11 | E11: =IFERROR((B11-C11)/B11,0) | F11: =IF(C11<=B11,"Under Budget","Over Budget")
A12: Entertainment | B12: 0 | C12: 0 | D12: =B12-C12 | E12: =IFERROR((B12-C12)/B12,0) | F12: =IF(C12<=B12,"Under Budget","Over Budget")
A13: Health | B13: 0 | C13: 0 | D13: =B13-C13 | E13: =IFERROR((B13-C13)/B13,0) | F13: =IF(C13<=B13,"Under Budget","Over Budget")
A14: Travel | B14: 0 | C14: 0 | D14: =B14-C14 | E14: =IFERROR((B14-C14)/B14,0) | F14: =IF(C14<=B14,"Under Budget","Over Budget")
A15: Subscriptions | B15: 0 | C15: 0 | D15: =B15-C15 | E15: =IFERROR((B15-C15)/B15,0) | F15: =IF(C15<=B15,"Under Budget","Over Budget")
A16: Personal Care | B16: 0 | C16: 0 | D16: =B16-C16 | E16: =IFERROR((B16-C16)/B16,0) | F16: =IF(C16<=B16,"Under Budget","Over Budget")
A17: Education | B17: 0 | C17: 0 | D17: =B17-C17 | E17: =IFERROR((B17-C17)/B17,0) | F17: =IF(C17<=B17,"Under Budget","Over Budget")
... A20: Other / Uncategorized | B20: 0 | C20: 0 | D20: =B20-C20 | E20: =IFERROR((B20-C20)/B20,0) | F20: =IF(C20<=B20,"Under Budget","Over Budget")
A21: TOTAL | B21: =SUM(B6:B20) | C21: =SUM(C6:C20) | D21: =SUM(D6:D20) | E21: =IFERROR((B21-C21)/B21,0) | F21: =IF(C21<=B21,"Under Budget","Over Budget")

Sheet Transaction Log
A1: Transaction Log – Raw Transaction Data
A3: Date | B3: Merchant / Description | C3: Amount | D3: Plaid Category | E3: App Category | F3: Account | G3: Pending | H3: Notes
A4: 2026-01-15 | B4: Whole Foods Market | C4: 87.32 | D4: Food and Drink > Groceries | E4: Groceries | F4: Checking ****1234 | G4: No
A5: 2026-01-15 | B5: Uber Eats | C5: 32.5 | D5: Food and Drink > Restaurants > Fast Food | E5: Dining Out | F5: Credit Card ****5678 | G5: No
A6: 2026-01-14 | B6: Shell Gas Station | C6: 45 | D6: Travel > Gas | E6: Transportation | F6: Credit Card ****5678 | G6: No
A7: 2026-01-14 | B7: Netflix | C7: 15.99 | D7: Service > Subscription | E7: Subscriptions | F7: Credit Card ****5678 | G7: No | H7: Monthly
A8: 2026-01-13 | B8: Target | C8: 124.56 | D8: Shops > General Merchandise | E8: Shopping | F8: Credit Card ****5678 | G8: Yes | H8: Pending
A9: 2026-01-13 | B9: Employer Direct Deposit | C9: -3500 | D9: Transfer > Payroll | E9: Income | F9: Checking ****1234 | G9: No | H9: Bi-weekly pay
A10: 2026-01-12 | B10: Walgreens Pharmacy | C10: 22.45 | D10: Healthcare > Pharmacy | E10: Health | F10: Credit Card ****5678 | G10: No
A11: 2026-01-12 | B11: Spotify | C11: 9.99 | D11: Service > Subscription | E11: Subscriptions | F11: Credit Card ****5678 | G11: No | H11: Monthly
A12: 2026-01-11 | B12: Rent Payment | C12: 1800 | D12: Payment > Rent | E12: Housing | F12: Checking ****1234 | G12: No | H12: Monthly rent
A13: 2026-01-10 | B13: Venmo Transfer | C13: 50 | D13: Transfer > Third Party | E13: Transfer | F13: Checking ****1234 | G13: No | H13: Split dinner

Sheet Assumptions & Notes
A1: Model Assumptions & Notes
A3: Topic | B3: Assumption | C3: Notes
A4: Data Source | B4: Plaid API (Sandbox mode for Phase 1) | C4: Production Plaid requires OAuth approval
A5: Category System | B5: 17 categories mapped from Plaid's 3-level hierarchy | C5: User overrides take priority over Plaid auto-categorization
A6: Transfer Handling | B6: Transfers excluded from income/expense totals | C6: Categorized separately to avoid double-counting
A7: Pending Transactions | B7: Included in log with 'Pending' flag | C7: Will update on next Plaid sync
A8: Income Recognition | B8: Income = negative amounts in Plaid (money flowing in) | C8: Payroll, refunds, interest (positive)
A9: Expense Recognition | B9: Expenses = positive amounts in Plaid (money flowing out) | C9: All spending categories
A10: Currency | B10: USD only for Phase 1 | C10: Multi-currency support out of scope
A11: Time Period | B11: Monthly reporting periods | C11: Calendar month boundaries
A12: Budget Method | B12: Zero-based budgeting approach | C12: Every dollar assigned a category
A13: Savings Rate | B13: =Net Cash Flow / Total Income | C13: Target: 20%+ for healthy finances
